commandrex/__init__.py
commandrex/__main__.py
commandrex/config/__init__.py
commandrex/config/api_manager.py
commandrex/config/settings.py
commandrex/executor/__init__.py
commandrex/executor/command_parser.py
commandrex/executor/platform_utils.py
commandrex/executor/platform_utils.py.bak
commandrex/executor/shell_manager.py
commandrex/main.py
commandrex/models/command_models.py
commandrex/translator/__init__.py
commandrex/translator/openai_client.py
commandrex/translator/prompt_builder.py
commandrex/translator/prompt_builder.py.bak
commandrex/ui/animations/universal.py
commandrex/ui/command_selector.py
commandrex/utils/__init__.py
commandrex/utils/logging.py
commandrex/utils/security.py
commandrex/utils/welcome_screen.py
commandrex/validator/command_validator.py
commandrex-0.2.dist-info/entry_points.txt
commandrex-0.2.dist-info/METADATA
commandrex-0.2.dist-info/WHEEL
commandrex-0.2.dist-info/RECORD
