Metadata-Version: 2.3
Name: commandrex
Version: 0.2
Summary: A natural language interface for terminal commands
License: MIT
Keywords: terminal,command-line,natural-language,openai,ai,cli,shell
Author: Siddhant
Requires-Python: >=3.10
Classifier: Development Status :: 4 - Beta
Classifier: Environment :: Console
Classifier: Intended Audience :: Developers
Classifier: Intended Audience :: System Administrators
Classifier: License :: OSI Approved :: MIT License
Classifier: Programming Language :: Python :: 3
Classifier: Programming Language :: Python :: 3.10
Classifier: Programming Language :: Python :: 3.11
Classifier: Programming Language :: Python :: 3.12
Classifier: Programming Language :: Python :: 3.13
Classifier: Topic :: System :: Shells
Classifier: Topic :: Utilities
Requires-Dist: httpx (>=0.28.1)
Requires-Dist: keyring (>=25.6.0)
Requires-Dist: openai (>=1.65.2)
Requires-Dist: pydantic (>=2.10.6)
Requires-Dist: python-dotenv (>=1.0.1)
Requires-Dist: rich (>=13.9.4)
Requires-Dist: typer (>=0.15.2)
Project-URL: Bug Tracker, https://github.com/siddhantparadox/commandrex-cli/issues
Project-URL: Documentation, https://github.com/siddhantparadox/commandrex-cli#readme
Project-URL: Homepage, https://github.com/siddhantparadox/commandrex-cli
